py_cryptotp/__init__.py
py_cryptotp/py_cryptotp.py
py_cryptotp/test.py
py_cryptotp-0.0.2.dist-info/AUTHORS.rst
py_cryptotp-0.0.2.dist-info/LICENSE
py_cryptotp-0.0.2.dist-info/METADATA
py_cryptotp-0.0.2.dist-info/WHEEL
py_cryptotp-0.0.2.dist-info/top_level.txt
py_cryptotp-0.0.2.dist-info/RECORD
