Metadata-Version: 2.1
Name: py-cryptotp
Version: 0.0.2
Summary: Generate and handle OTP or 2 step verifications easily and securely without using any DATABASES.
Home-page: https://github.com/shamimferdous/py_cryptotp
Author: Shamim Ferdous
Author-email: shamimferdous5@gmail.com
License: MIT license
Keywords: py_cryptotp
Platform: UNKNOWN
Classifier: Development Status :: 4 - Beta
Classifier: Intended Audience :: Developers
Classifier: License :: OSI Approved :: MIT License
Classifier: Natural Language :: English
Classifier: Programming Language :: Python :: 3
Classifier: Programming Language :: Python :: 3.5
Classifier: Programming Language :: Python :: 3.6
Classifier: Programming Language :: Python :: 3.7
Classifier: Programming Language :: Python :: 3.8
Requires-Python: >=3.5
